pyas2lib/__init__.py
pyas2lib/as2.py
pyas2lib/cms.py
pyas2lib/compat.py
pyas2lib/constants.py
pyas2lib/exceptions.py
pyas2lib/utils.py
pyas2lib/tests/__init__.py
pyas2lib/tests/livetest_with_mecas2.py
pyas2lib/tests/livetest_with_oldpyas2.py
pyas2lib/tests/test_advanced.py
pyas2lib/tests/test_basic.py
pyas2lib/tests/test_cms.py
pyas2lib/tests/test_mdn.py
pyas2lib/tests/test_utils.py
pyas2lib/tests/test_with_mecas2.py
pyas2lib-1.4.4.dist-info/AUTHORS.md
pyas2lib-1.4.4.dist-info/LICENSE
pyas2lib-1.4.4.dist-info/METADATA
pyas2lib-1.4.4.dist-info/WHEEL
pyas2lib-1.4.4.dist-info/top_level.txt
pyas2lib-1.4.4.dist-info/RECORD
